lightrag_memgraph/__init__.py
lightrag_memgraph/core.py
lightrag_memgraph-0.1.3.dist-info/METADATA
lightrag_memgraph-0.1.3.dist-info/WHEEL
lightrag_memgraph-0.1.3.dist-info/licenses/LICENSE
lightrag_memgraph-0.1.3.dist-info/RECORD
